aico_guard_mcp_server/__init__.py
aico_guard_mcp_server/guard_mcp_server.py
aico_guard_mcp_server/utils.py
antdigital_aico_guard_mcp_server-0.1.3.dist-info/METADATA
antdigital_aico_guard_mcp_server-0.1.3.dist-info/WHEEL
antdigital_aico_guard_mcp_server-0.1.3.dist-info/entry_points.txt
antdigital_aico_guard_mcp_server-0.1.3.dist-info/RECORD
