Metadata-Version: 2.4
Name: antdigital-aico-guard-mcp-server
Version: 0.1.3
Summary: Ant guard mcp server
Requires-Python: >=3.10
Requires-Dist: antchain-aitechguard==1.0.26
Requires-Dist: fastmcp==2.2.5
Requires-Dist: httpx==0.28.1
Requires-Dist: requests>=2.32.3
